tx/functional/__init__.py
tx/functional/applicative.py
tx/functional/either.py
tx/functional/functor.py
tx/functional/list.py
tx/functional/maybe.py
tx/functional/monad.py
tx/functional/traversable.py
tx/functional/utils.py
tx_functional-0.1.2.dist-info/LICENSE
tx_functional-0.1.2.dist-info/METADATA
tx_functional-0.1.2.dist-info/WHEEL
tx_functional-0.1.2.dist-info/top_level.txt
tx_functional-0.1.2.dist-info/RECORD
