Metadata-Version: 2.1
Name: tx-functional
Version: 0.1.2
Summary: A pickleable generic functional programming library
Home-page: https://github.com/RENCI/tx-functional
Author: Hao Xu
Author-email: xuhao@renci.org
License: MIT
Platform: UNKNOWN
Classifier: Programming Language :: Python :: 3
Classifier: License :: OSI Approved :: MIT License
Classifier: Operating System :: OS Independent
Requires-Python: >=3.6
